LICENSE
MANIFEST.in
README.md
setup.py
django_google_auth2/__init__.py
django_google_auth2/admin.py
django_google_auth2/apps.py
django_google_auth2/models.py
django_google_auth2/tests.py
django_google_auth2/urls.py
django_google_auth2/views.py
django_google_auth2.egg-info/PKG-INFO
django_google_auth2.egg-info/SOURCES.txt
django_google_auth2.egg-info/dependency_links.txt
django_google_auth2.egg-info/top_level.txt
django_google_auth2/google/bindgoogleauth/bindgoogleauth.py
django_google_auth2/google/bindgoogleauth/bindgoogleauthapi.py
django_google_auth2/google/bindgoogleauth/__pycache__/bindgoogleauth.cpython-36.pyc
django_google_auth2/google/bindgoogleauth/__pycache__/bindgoogleauthapi.cpython-36.pyc
django_google_auth2/google/checkgoogleauth/checkgoogleauth.py
django_google_auth2/google/checkgoogleauth/__pycache__/checkgoogleauth.cpython-36.pyc
django_google_auth2/google/deletegoogleauth/deletegoogleauth.py
django_google_auth2/google/deletegoogleauth/__pycache__/deletegoogleauth.cpython-36.pyc
django_google_auth2/migrations/.DS_Store
django_google_auth2/migrations/__init__.py
django_google_auth2/migrations/__pycache__/0001_initial.cpython-36.pyc
django_google_auth2/migrations/__pycache__/__init__.cpython-36.pyc
django_google_auth2/templates/google.html
django_google_auth2/templatetags/otp_tags.py
django_google_auth2/templatetags/__pycache__/otp_tags.cpython-36.pyc
django_google_auth2/utils/googleotp/googleotp.py
django_google_auth2/utils/googleotp/__pycache__/googleotp.cpython-36.pyc
django_google_auth2/utils/googletotp/googletotp.py
django_google_auth2/utils/googletotp/__pycache__/googletotp.cpython-36.pyc
django_google_auth2/utils/googleutils/googleutils.py
django_google_auth2/utils/googleutils/__pycache__/googleutils.cpython-36.pyc
django_google_auth2/utils/googleverify/googleverify.py