Metadata-Version: 1.1
Name: django-google-auth2
Version: 0.0.8
Summary: django-google-auth2 project is demo application for google auth 
Home-page: https://github.com/Coxhuang/django-google-auth
Author: 黄民航
Author-email: gmhesat@gmail.com
License: BSD License
Platform: UNKNOWN
Classifier: Environment :: Web Environment
Classifier: Framework :: Django
Classifier: Framework :: Django :: 2.0
Classifier: Intended Audience :: Developers
Classifier: License :: OSI Approved :: BSD License
Classifier: Operating System :: OS Independent
Classifier: Programming Language :: Python
Classifier: Programming Language :: Python :: 2
Classifier: Programming Language :: Python :: 3.6
